{
    "date": "2016/12/3 14:10:49",
    "game_id": "789978882",
    "variant": "PRR",
    "table_name": "Ekek-14",
    "type_game": "Hold'em",
    "button_seat": 1,
    "players": [
        "bludrifter",
        "IlxxxlI",
        "David_lay",
        "Jui Kuen",
        "giveitback",
        "CalmDownJustCall"
    ],
    "players_seats": [
        1,
        2,
        3,
        4,
        5,
        6
    ],
    "starting_stacks": [
        16.75,
        10.0,
        28.75,
        28.03,
        30.12,
        26.67
    ],
    "player_small_blind": "IlxxxlI",
    "small_blind": 0.1,
    "player_big_blind": "David_lay",
    "big_blind": 0.25,
    "player": "IlxxxlI",
    "cards_player": [
        "9d",
        "5d"
    ],
    "dealed_cards": {
        "flop": [
            "2s",
            "8d",
            "2c"
        ],
        "turn": [],
        "river": []
    },
    "actions": {
        "pre-flop": {
            "players": [
                "Jui Kuen",
                "giveitback",
                "CalmDownJustCall",
                "bludrifter",
                "IlxxxlI",
                "David_lay"
            ],
            "actions": [
                "FOLD",
                "FOLD",
                "FOLD",
                "FOLD",
                "CALL",
                "CHECK"
            ],
            "values": [
                null,
                null,
                null,
                null,
                0.15,
                null
            ]
        },
        "post-flop": {
            "players": [
                "IlxxxlI",
                "David_lay"
            ],
            "actions": [
                "BET",
                "FOLD"
            ],
            "values": [
                0.32,
                null
            ]
        },
        "post-turn": {
            "players": [],
            "actions": [],
            "values": []
        },
        "post-river": {
            "players": [],
            "actions": [],
            "values": []
        }
    },
    "card_shown_by_players": [
        null,
        null,
        null,
        null,
        null,
        null
    ],
    "finishing_stack": [
        16.75,
        10.23,
        28.5,
        28.03,
        30.12,
        26.67
    ]
}