{
    "date": "2016/10/10 20:47:17",
    "game_id": "747587057",
    "variant": "PRR",
    "table_name": "Garuda",
    "type_game": "Hold'em",
    "button_seat": 4,
    "players": [
        "MrYosh",
        "icantstop",
        "Parcker",
        "StackMagic",
        "imperceptible",
        "....",
        "HotSauce3",
        "IlxxxlI"
    ],
    "players_seats": [
        1,
        2,
        3,
        4,
        5,
        6,
        8,
        9
    ],
    "starting_stacks": [
        72.48,
        130.89,
        53.74,
        53.48,
        16.02,
        72.49,
        39.51,
        50.0
    ],
    "player_small_blind": "imperceptible",
    "small_blind": 0.25,
    "player_big_blind": "....",
    "big_blind": 0.5,
    "player": "IlxxxlI",
    "cards_player": [
        "3d",
        "Kh"
    ],
    "dealed_cards": {
        "flop": [
            "9c",
            "5s",
            "2d"
        ],
        "turn": [
            "2s"
        ],
        "river": []
    },
    "actions": {
        "pre-flop": {
            "players": [
                "HotSauce3",
                "IlxxxlI",
                "MrYosh",
                "icantstop",
                "Parcker",
                "StackMagic",
                "imperceptible",
                "...."
            ],
            "actions": [
                "FOLD",
                "FOLD",
                "RAISE",
                "CALL",
                "FOLD",
                "FOLD",
                "FOLD",
                "FOLD"
            ],
            "values": [
                null,
                null,
                1.5,
                1.5,
                null,
                null,
                null,
                null
            ]
        },
        "post-flop": {
            "players": [
                "MrYosh",
                "icantstop"
            ],
            "actions": [
                "BET",
                "CALL"
            ],
            "values": [
                2.08,
                2.08
            ]
        },
        "post-turn": {
            "players": [
                "MrYosh",
                "icantstop"
            ],
            "actions": [
                "BET",
                "FOLD"
            ],
            "values": [
                5.2,
                null
            ]
        },
        "post-river": {
            "players": [],
            "actions": [],
            "values": []
        }
    },
    "card_shown_by_players": [
        null,
        null,
        null,
        null,
        null,
        null,
        null,
        null
    ],
    "finishing_stack": [
        76.42,
        127.30999999999999,
        53.74,
        53.48,
        15.77,
        71.99,
        39.51,
        50.0
    ]
}