{
    "date": "2016/11/29 14:47:48",
    "game_id": "787014536",
    "variant": "PRR",
    "table_name": "Karkadann-3",
    "type_game": "Hold'em",
    "button_seat": 4,
    "players": [
        "ElvenEyes",
        "StephCurry",
        "gust",
        "pineapplesand",
        "AironVega",
        "IlxxxlI",
        "dankmann",
        "VegetablesArentYummy"
    ],
    "players_seats": [
        2,
        3,
        4,
        5,
        6,
        7,
        8,
        9
    ],
    "starting_stacks": [
        165.75,
        101.5,
        51.95,
        42.46,
        102.28,
        43.0,
        154.69,
        257.91
    ],
    "player_small_blind": "pineapplesand",
    "small_blind": 0.5,
    "player_big_blind": "AironVega",
    "big_blind": 1.0,
    "player": "IlxxxlI",
    "cards_player": [
        "Ks",
        "Qc"
    ],
    "dealed_cards": {
        "flop": [],
        "turn": [],
        "river": []
    },
    "actions": {
        "pre-flop": {
            "players": [
                "IlxxxlI",
                "dankmann",
                "VegetablesArentYummy",
                "ElvenEyes",
                "StephCurry",
                "gust",
                "pineapplesand",
                "AironVega"
            ],
            "actions": [
                "RAISE",
                "FOLD",
                "FOLD",
                "FOLD",
                "FOLD",
                "FOLD",
                "FOLD",
                "FOLD"
            ],
            "values": [
                3.5,
                null,
                null,
                null,
                null,
                null,
                null,
                null
            ]
        },
        "post-flop": {
            "players": [],
            "actions": [],
            "values": []
        },
        "post-turn": {
            "players": [],
            "actions": [],
            "values": []
        },
        "post-river": {
            "players": [],
            "actions": [],
            "values": []
        }
    },
    "card_shown_by_players": [
        null,
        null,
        null,
        null,
        null,
        null,
        null,
        null
    ],
    "finishing_stack": [
        165.75,
        101.5,
        51.95,
        41.96,
        101.28,
        44.5,
        154.69,
        257.91
    ]
}