{
    "date": "2016/12/8 17:20:28",
    "game_id": "793444620",
    "variant": "PRR",
    "table_name": "Ekek-9",
    "type_game": "Hold'em",
    "button_seat": 6,
    "players": [
        "needmorefppp",
        "Aaron.o_O",
        "renoreno",
        "IlxxxlI",
        "Moryak999",
        "boosaz"
    ],
    "players_seats": [
        1,
        2,
        3,
        4,
        5,
        6
    ],
    "starting_stacks": [
        38.89,
        26.13,
        25.21,
        10.0,
        24.65,
        29.15
    ],
    "player_small_blind": "needmorefppp",
    "small_blind": 0.1,
    "player_big_blind": "Aaron.o_O",
    "big_blind": 0.25,
    "player": "IlxxxlI",
    "cards_player": [
        "2s",
        "Ad"
    ],
    "dealed_cards": {
        "flop": [],
        "turn": [],
        "river": []
    },
    "actions": {
        "pre-flop": {
            "players": [
                "renoreno",
                "IlxxxlI",
                "Moryak999",
                "boosaz",
                "needmorefppp"
            ],
            "actions": [
                "FOLD",
                "FOLD",
                "FOLD",
                "FOLD",
                "FOLD"
            ],
            "values": [
                null,
                null,
                null,
                null,
                null
            ]
        },
        "post-flop": {
            "players": [],
            "actions": [],
            "values": []
        },
        "post-turn": {
            "players": [],
            "actions": [],
            "values": []
        },
        "post-river": {
            "players": [],
            "actions": [],
            "values": []
        }
    },
    "card_shown_by_players": [
        null,
        null,
        null,
        null,
        null,
        null
    ],
    "finishing_stack": [
        38.79,
        26.229999999999997,
        25.21,
        10.0,
        24.65,
        29.15
    ]
}