{
    "date": "2016/12/1 15:53:23",
    "game_id": "788670339",
    "variant": "PRR",
    "table_name": "Lakhey",
    "type_game": "Hold'em",
    "button_seat": 2,
    "players": [
        "flyshark01",
        "LoadRage",
        "IlxxxlI",
        "SHER1FFmd"
    ],
    "players_seats": [
        1,
        2,
        4,
        6
    ],
    "starting_stacks": [
        353.36,
        253.52,
        104.08,
        200.0
    ],
    "player_small_blind": "IlxxxlI",
    "small_blind": 1.0,
    "player_big_blind": "SHER1FFmd",
    "big_blind": 2.0,
    "player": "IlxxxlI",
    "cards_player": [
        "10h",
        "7h"
    ],
    "dealed_cards": {
        "flop": [
            "4c",
            "Kh",
            "5d"
        ],
        "turn": [
            "7c"
        ],
        "river": [
            "2c"
        ]
    },
    "actions": {
        "pre-flop": {
            "players": [
                "flyshark01",
                "LoadRage",
                "IlxxxlI",
                "SHER1FFmd"
            ],
            "actions": [
                "RAISE",
                "CALL",
                "FOLD",
                "FOLD"
            ],
            "values": [
                6.0,
                6.0,
                null,
                null
            ]
        },
        "post-flop": {
            "players": [
                "flyshark01",
                "LoadRage"
            ],
            "actions": [
                "CHECK",
                "CHECK"
            ],
            "values": [
                null,
                null
            ]
        },
        "post-turn": {
            "players": [
                "flyshark01",
                "LoadRage"
            ],
            "actions": [
                "CHECK",
                "CHECK"
            ],
            "values": [
                null,
                null
            ]
        },
        "post-river": {
            "players": [
                "flyshark01",
                "LoadRage"
            ],
            "actions": [
                "CHECK",
                "CHECK"
            ],
            "values": [
                null,
                null
            ]
        }
    },
    "card_shown_by_players": [
        null,
        "4s 3s",
        null,
        null
    ],
    "finishing_stack": [
        347.36,
        261.77,
        103.08,
        198.0
    ]
}