{
    "date": "2016/9/5 12:12:41",
    "game_id": "720261268",
    "variant": "PRR",
    "table_name": "Longana",
    "type_game": "Short",
    "button_seat": 6,
    "players": [
        "UrSoDumb",
        "St3p04ka",
        "IlxxxlI",
        "AironVega",
        "gust",
        "Marketsniper",
        "jtee95",
        "norcalho",
        "lars76"
    ],
    "players_seats": [
        1,
        2,
        3,
        4,
        5,
        6,
        7,
        8,
        9
    ],
    "starting_stacks": [
        239.55,
        120.25,
        43.0,
        264.34,
        96.0,
        91.4,
        161.42,
        40.0,
        115.65
    ],
    "player_small_blind": "jtee95",
    "small_blind": 1.0,
    "player_big_blind": "norcalho",
    "big_blind": 2.0,
    "player": "IlxxxlI",
    "cards_player": [
        "3s",
        "Js"
    ],
    "dealed_cards": {
        "flop": [],
        "turn": [],
        "river": []
    },
    "actions": {
        "pre-flop": {
            "players": [
                "lars76",
                "UrSoDumb",
                "St3p04ka",
                "IlxxxlI",
                "AironVega",
                "gust",
                "Marketsniper",
                "jtee95",
                "norcalho",
                "gust"
            ],
            "actions": [
                "FOLD",
                "FOLD",
                "FOLD",
                "FOLD",
                "FOLD",
                "RAISE",
                "RAISE",
                "FOLD",
                "FOLD",
                "FOLD"
            ],
            "values": [
                null,
                null,
                null,
                null,
                null,
                4.0,
                14.0,
                null,
                null,
                null
            ]
        },
        "post-flop": {
            "players": [],
            "actions": [],
            "values": []
        },
        "post-turn": {
            "players": [],
            "actions": [],
            "values": []
        },
        "post-river": {
            "players": [],
            "actions": [],
            "values": []
        }
    },
    "card_shown_by_players": [
        null,
        null,
        null,
        null,
        null,
        null,
        null,
        null,
        null
    ],
    "finishing_stack": [
        239.55,
        120.25,
        43.0,
        264.34,
        92.0,
        98.4,
        160.42,
        38.0,
        115.65
    ]
}