{
    "date": "2016/9/6 0:39:11",
    "game_id": "720642132",
    "variant": "PRR",
    "table_name": "Lakhey",
    "type_game": "Short",
    "button_seat": 3,
    "players": [
        "TJoseph1",
        "IlxxxlI",
        "Ksowas",
        "JikkiP",
        "Im Don King"
    ],
    "players_seats": [
        2,
        3,
        4,
        5,
        6
    ],
    "starting_stacks": [
        55.25,
        115.75,
        221.79,
        100.0,
        100.0
    ],
    "player_small_blind": "Ksowas",
    "small_blind": 1.0,
    "player_big_blind": "JikkiP",
    "big_blind": 2.0,
    "player": "IlxxxlI",
    "cards_player": [
        "9c",
        "4c"
    ],
    "dealed_cards": {
        "flop": [],
        "turn": [],
        "river": []
    },
    "actions": {
        "pre-flop": {
            "players": [
                "Im Don King",
                "TJoseph1",
                "IlxxxlI",
                "Ksowas"
            ],
            "actions": [
                "FOLD",
                "FOLD",
                "FOLD",
                "FOLD"
            ],
            "values": [
                null,
                null,
                null,
                null
            ]
        },
        "post-flop": {
            "players": [],
            "actions": [],
            "values": []
        },
        "post-turn": {
            "players": [],
            "actions": [],
            "values": []
        },
        "post-river": {
            "players": [],
            "actions": [],
            "values": []
        }
    },
    "card_shown_by_players": [
        null,
        null,
        null,
        null,
        null
    ],
    "finishing_stack": [
        55.25,
        115.75,
        220.79,
        101.0,
        100.0
    ]
}