{
    "date": "2016/9/18 7:27:53",
    "game_id": "730184827",
    "variant": "PRR",
    "table_name": "Longana",
    "type_game": "Hold'em",
    "button_seat": 5,
    "players": [
        "A",
        "IlxxxlI",
        "Pimpika",
        "drdboy",
        "utormico",
        "wishyouhadnot",
        "BadBeat79",
        "UrSoDumb",
        "KeepKalm"
    ],
    "players_seats": [
        1,
        2,
        3,
        4,
        5,
        6,
        7,
        8,
        9
    ],
    "starting_stacks": [
        302.46,
        83.6,
        83.45,
        89.73,
        172.51,
        189.05,
        296.23,
        315.26,
        203.0
    ],
    "player_small_blind": "wishyouhadnot",
    "small_blind": 1.0,
    "player_big_blind": "BadBeat79",
    "big_blind": 2.0,
    "player": "IlxxxlI",
    "cards_player": [
        "3c",
        "2d"
    ],
    "dealed_cards": {
        "flop": [],
        "turn": [],
        "river": []
    },
    "actions": {
        "pre-flop": {
            "players": [
                "UrSoDumb",
                "KeepKalm",
                "A",
                "IlxxxlI",
                "Pimpika",
                "drdboy",
                "utormico",
                "wishyouhadnot",
                "BadBeat79"
            ],
            "actions": [
                "FOLD",
                "FOLD",
                "FOLD",
                "FOLD",
                "FOLD",
                "FOLD",
                "FOLD",
                "RAISE",
                "FOLD"
            ],
            "values": [
                null,
                null,
                null,
                null,
                null,
                null,
                null,
                7.0,
                null
            ]
        },
        "post-flop": {
            "players": [],
            "actions": [],
            "values": []
        },
        "post-turn": {
            "players": [],
            "actions": [],
            "values": []
        },
        "post-river": {
            "players": [],
            "actions": [],
            "values": []
        }
    },
    "card_shown_by_players": [
        null,
        null,
        null,
        null,
        null,
        null,
        null,
        null,
        null
    ],
    "finishing_stack": [
        302.46,
        83.6,
        83.45,
        89.73,
        172.51,
        191.05,
        294.23,
        315.26,
        203.0
    ]
}