{
    "date": "2016/12/9 9:7:26",
    "game_id": "793886391",
    "variant": "PRR",
    "table_name": "Kraken-14",
    "type_game": "Hold'em",
    "button_seat": 1,
    "players": [
        "WeakAndWeary",
        "MadLifeGrinder",
        "VegetablesArentYummy",
        "IlxxxlI",
        "Heksebrygg"
    ],
    "players_seats": [
        1,
        2,
        3,
        4,
        5
    ],
    "starting_stacks": [
        141.6,
        103.23,
        104.0,
        40.0,
        163.56
    ],
    "player_small_blind": "MadLifeGrinder",
    "small_blind": 0.5,
    "player_big_blind": "IlxxxlI",
    "big_blind": 1.0,
    "player": "IlxxxlI",
    "cards_player": [
        "5s",
        "10h"
    ],
    "dealed_cards": {
        "flop": [],
        "turn": [],
        "river": []
    },
    "actions": {
        "pre-flop": {
            "players": [
                "Heksebrygg",
                "WeakAndWeary",
                "MadLifeGrinder",
                "IlxxxlI"
            ],
            "actions": [
                "FOLD",
                "FOLD",
                "RAISE",
                "FOLD"
            ],
            "values": [
                null,
                null,
                2.5,
                null
            ]
        },
        "post-flop": {
            "players": [],
            "actions": [],
            "values": []
        },
        "post-turn": {
            "players": [],
            "actions": [],
            "values": []
        },
        "post-river": {
            "players": [],
            "actions": [],
            "values": []
        }
    },
    "card_shown_by_players": [
        null,
        null,
        null,
        null,
        null
    ],
    "finishing_stack": [
        141.6,
        104.23,
        104.0,
        39.0,
        163.56
    ]
}