{
    "date": "2016/9/5 12:54:53",
    "game_id": "720273177",
    "variant": "PRR",
    "table_name": "Longana",
    "type_game": "Short",
    "button_seat": 4,
    "players": [
        "St3p04ka",
        "IlxxxlI",
        "pokerhawk333",
        "jtee95",
        "PANDAisEVIL"
    ],
    "players_seats": [
        2,
        3,
        4,
        7,
        8
    ],
    "starting_stacks": [
        125.41,
        40.0,
        35.87,
        227.28,
        138.77
    ],
    "player_small_blind": "jtee95",
    "small_blind": 1.0,
    "player_big_blind": "PANDAisEVIL",
    "big_blind": 2.0,
    "player": "IlxxxlI",
    "cards_player": [
        "5d",
        "4h"
    ],
    "dealed_cards": {
        "flop": [
            "9d",
            "4d",
            "2d"
        ],
        "turn": [],
        "river": []
    },
    "actions": {
        "pre-flop": {
            "players": [
                "St3p04ka",
                "IlxxxlI",
                "pokerhawk333",
                "jtee95",
                "PANDAisEVIL"
            ],
            "actions": [
                "FOLD",
                "FOLD",
                "RAISE",
                "CALL",
                "FOLD"
            ],
            "values": [
                null,
                null,
                4.0,
                3.0,
                null
            ]
        },
        "post-flop": {
            "players": [
                "jtee95",
                "pokerhawk333",
                "jtee95",
                "pokerhawk333"
            ],
            "actions": [
                "CHECK",
                "BET",
                "RAISE",
                "FOLD"
            ],
            "values": [
                null,
                4.75,
                14.25,
                null
            ]
        },
        "post-turn": {
            "players": [],
            "actions": [],
            "values": []
        },
        "post-river": {
            "players": [],
            "actions": [],
            "values": []
        }
    },
    "card_shown_by_players": [
        null,
        null,
        null,
        null,
        null
    ],
    "finishing_stack": [
        125.41,
        40.0,
        27.119999999999997,
        237.06,
        136.77
    ]
}