{
    "date": "2016/12/7 9:22:20",
    "game_id": "792495373",
    "variant": "PRR",
    "table_name": "Ekek-7",
    "type_game": "Hold'em",
    "button_seat": 3,
    "players": [
        "Ice Bank Mice Elf",
        "ABMTLQC",
        "KingLewi2988",
        "Irene13",
        "IlxxxlI",
        "t0x1cAce"
    ],
    "players_seats": [
        1,
        2,
        3,
        4,
        5,
        6
    ],
    "starting_stacks": [
        45.3,
        25.0,
        27.3,
        31.99,
        10.0,
        13.77
    ],
    "player_small_blind": "Irene13",
    "small_blind": 0.1,
    "player_big_blind": "IlxxxlI",
    "big_blind": 0.25,
    "player": "IlxxxlI",
    "cards_player": [
        "10c",
        "2s"
    ],
    "dealed_cards": {
        "flop": [
            "9s",
            "4s",
            "Js"
        ],
        "turn": [],
        "river": []
    },
    "actions": {
        "pre-flop": {
            "players": [
                "t0x1cAce",
                "Ice Bank Mice Elf",
                "ABMTLQC",
                "KingLewi2988",
                "Irene13",
                "IlxxxlI"
            ],
            "actions": [
                "RAISE",
                "CALL",
                "FOLD",
                "FOLD",
                "FOLD",
                "FOLD"
            ],
            "values": [
                0.7,
                0.7,
                null,
                null,
                null,
                null
            ]
        },
        "post-flop": {
            "players": [
                "t0x1cAce",
                "Ice Bank Mice Elf",
                "t0x1cAce"
            ],
            "actions": [
                "CHECK",
                "BET",
                "FOLD"
            ],
            "values": [
                null,
                1.11,
                null
            ]
        },
        "post-turn": {
            "players": [],
            "actions": [],
            "values": []
        },
        "post-river": {
            "players": [],
            "actions": [],
            "values": []
        }
    },
    "card_shown_by_players": [
        null,
        null,
        null,
        null,
        null,
        null
    ],
    "finishing_stack": [
        46.269999999999996,
        25.0,
        27.3,
        31.889999999999997,
        9.75,
        13.07
    ]
}