{
    "date": "2016/12/25 0:6:8",
    "game_id": "805283925",
    "variant": "PRR",
    "table_name": "Ekek",
    "type_game": "Cap",
    "button_seat": 5,
    "players": [
        "MrZPoker",
        "Jerin.J.",
        "booya25",
        "IlxxxlI",
        "N1cer1ver",
        "Log_in"
    ],
    "players_seats": [
        1,
        2,
        3,
        4,
        5,
        6
    ],
    "starting_stacks": [
        16.12,
        3.83,
        25.49,
        46.32,
        25.0,
        8.74
    ],
    "player_small_blind": "Log_in",
    "small_blind": 0.1,
    "player_big_blind": "MrZPoker",
    "big_blind": 0.25,
    "player": "IlxxxlI",
    "cards_player": [
        "4c",
        "Ad"
    ],
    "dealed_cards": {
        "flop": [
            "2h",
            "10h",
            "4d"
        ],
        "turn": [
            "Qh"
        ],
        "river": [
            "Kc"
        ]
    },
    "actions": {
        "pre-flop": {
            "players": [
                "Jerin.J.",
                "booya25",
                "IlxxxlI",
                "N1cer1ver",
                "Log_in",
                "MrZPoker",
                "Jerin.J.",
                "N1cer1ver"
            ],
            "actions": [
                "RAISE",
                "FOLD",
                "FOLD",
                "RAISE",
                "FOLD",
                "FOLD",
                "ALLIN",
                "CALL"
            ],
            "values": [
                0.75,
                null,
                null,
                2.75,
                null,
                null,
                3.08,
                1.08
            ]
        },
        "post-flop": {
            "players": [],
            "actions": [],
            "values": []
        },
        "post-turn": {
            "players": [],
            "actions": [],
            "values": []
        },
        "post-river": {
            "players": [],
            "actions": [],
            "values": []
        }
    },
    "card_shown_by_players": [
        null,
        "8c 8d",
        null,
        null,
        "As Js",
        null
    ],
    "finishing_stack": [
        15.870000000000001,
        0.0,
        25.49,
        46.32,
        28.78,
        8.64
    ]
}