{
    "date": "2016/12/2 22:58:32",
    "game_id": "789434100",
    "variant": "PRR",
    "table_name": "Lakhey-4",
    "type_game": "Hold'em",
    "button_seat": 4,
    "players": [
        "AironVega",
        "PANDAisEVIL",
        "1Rosenborg",
        "Chubrica",
        "IlxxxlI",
        "MikeMitch"
    ],
    "players_seats": [
        1,
        2,
        3,
        4,
        5,
        6
    ],
    "starting_stacks": [
        219.78,
        200.0,
        112.25,
        210.15,
        80.05,
        183.83
    ],
    "player_small_blind": "IlxxxlI",
    "small_blind": 1.0,
    "player_big_blind": "MikeMitch",
    "big_blind": 2.0,
    "player": "IlxxxlI",
    "cards_player": [
        "9d",
        "10c"
    ],
    "dealed_cards": {
        "flop": [
            "6d",
            "10s",
            "4h"
        ],
        "turn": [],
        "river": []
    },
    "actions": {
        "pre-flop": {
            "players": [
                "AironVega",
                "PANDAisEVIL",
                "1Rosenborg",
                "Chubrica",
                "IlxxxlI",
                "MikeMitch"
            ],
            "actions": [
                "FOLD",
                "FOLD",
                "RAISE",
                "FOLD",
                "FOLD",
                "CALL"
            ],
            "values": [
                null,
                null,
                4.0,
                null,
                null,
                2.0
            ]
        },
        "post-flop": {
            "players": [
                "MikeMitch",
                "1Rosenborg",
                "MikeMitch"
            ],
            "actions": [
                "CHECK",
                "BET",
                "FOLD"
            ],
            "values": [
                null,
                5.7,
                null
            ]
        },
        "post-turn": {
            "players": [],
            "actions": [],
            "values": []
        },
        "post-river": {
            "players": [],
            "actions": [],
            "values": []
        }
    },
    "card_shown_by_players": [
        null,
        null,
        null,
        null,
        null,
        null
    ],
    "finishing_stack": [
        219.78,
        200.0,
        116.8,
        210.15,
        79.05,
        179.83
    ]
}