{
    "date": "2016/12/9 14:0:20",
    "game_id": "794089872",
    "variant": "PRR",
    "table_name": "Gorgons-14",
    "type_game": "Hold'em",
    "button_seat": 4,
    "players": [
        "POSSUM9",
        "Xobkcul",
        "IlxxxlI",
        "yourcookie",
        "Mdwells",
        "WeakAndWeary"
    ],
    "players_seats": [
        1,
        2,
        3,
        4,
        5,
        6
    ],
    "starting_stacks": [
        63.2,
        55.17,
        24.49,
        42.22,
        30.26,
        66.1
    ],
    "player_small_blind": "Mdwells",
    "small_blind": 0.25,
    "player_big_blind": "WeakAndWeary",
    "big_blind": 0.5,
    "player": "IlxxxlI",
    "cards_player": [
        "3s",
        "2h"
    ],
    "dealed_cards": {
        "flop": [
            "7c",
            "6s",
            "9h"
        ],
        "turn": [
            "5h"
        ],
        "river": []
    },
    "actions": {
        "pre-flop": {
            "players": [
                "POSSUM9",
                "Xobkcul",
                "IlxxxlI",
                "yourcookie",
                "Mdwells",
                "WeakAndWeary"
            ],
            "actions": [
                "RAISE",
                "FOLD",
                "FOLD",
                "FOLD",
                "FOLD",
                "CALL"
            ],
            "values": [
                1.5,
                null,
                null,
                null,
                null,
                1.0
            ]
        },
        "post-flop": {
            "players": [
                "WeakAndWeary",
                "POSSUM9"
            ],
            "actions": [
                "CHECK",
                "CHECK"
            ],
            "values": [
                null,
                null
            ]
        },
        "post-turn": {
            "players": [
                "WeakAndWeary",
                "POSSUM9"
            ],
            "actions": [
                "BET",
                "FOLD"
            ],
            "values": [
                2.06,
                null
            ]
        },
        "post-river": {
            "players": [],
            "actions": [],
            "values": []
        }
    },
    "card_shown_by_players": [
        null,
        null,
        null,
        null,
        null,
        null
    ],
    "finishing_stack": [
        61.7,
        55.17,
        24.49,
        42.22,
        30.01,
        67.69
    ]
}