{
    "date": "2016/12/5 10:16:8",
    "game_id": "791314829",
    "variant": "PRR",
    "table_name": "Kraken-9",
    "type_game": "Hold'em",
    "button_seat": 3,
    "players": [
        "St3p04ka",
        "IlxxxlI",
        "flyshark01",
        "MadLifeGrinder",
        "rivergods"
    ],
    "players_seats": [
        2,
        3,
        4,
        5,
        6
    ],
    "starting_stacks": [
        42.5,
        48.75,
        227.82,
        100.0,
        141.69
    ],
    "player_small_blind": "flyshark01",
    "small_blind": 0.5,
    "player_big_blind": "MadLifeGrinder",
    "big_blind": 1.0,
    "player": "IlxxxlI",
    "cards_player": [
        "Js",
        "7d"
    ],
    "dealed_cards": {
        "flop": [],
        "turn": [],
        "river": []
    },
    "actions": {
        "pre-flop": {
            "players": [
                "rivergods",
                "St3p04ka",
                "IlxxxlI",
                "flyshark01",
                "MadLifeGrinder"
            ],
            "actions": [
                "RAISE",
                "FOLD",
                "FOLD",
                "FOLD",
                "FOLD"
            ],
            "values": [
                3.0,
                null,
                null,
                null,
                null
            ]
        },
        "post-flop": {
            "players": [],
            "actions": [],
            "values": []
        },
        "post-turn": {
            "players": [],
            "actions": [],
            "values": []
        },
        "post-river": {
            "players": [],
            "actions": [],
            "values": []
        }
    },
    "card_shown_by_players": [
        null,
        null,
        null,
        null,
        null
    ],
    "finishing_stack": [
        42.5,
        48.75,
        227.32,
        99.0,
        143.19
    ]
}